sensei/__init__.py
sensei/__main__.py
sensei/agent.py
sensei/cli.py
sensei/config.py
sensei/core.py
sensei/deps.py
sensei/paths.py
sensei/prompts.py
sensei/server.py
sensei/types.py
sensei/unified.py
sensei/api/__init__.py
sensei/api/__main__.py
sensei/api/models.py
sensei/database/__init__.py
sensei/database/local.py
sensei/database/models.py
sensei/database/storage.py
sensei/dojo/__init__.py
sensei/eval/__init__.py
sensei/eval/__main__.py
sensei/eval/datasets.py
sensei/eval/evaluators.py
sensei/eval/runner.py
sensei/eval/task.py
sensei/eval/datasets/fastapi.yaml
sensei/eval/datasets/general.yaml
sensei/eval/datasets/react.yaml
sensei/kura/__init__.py
sensei/kura/__main__.py
sensei/kura/server.py
sensei/kura/tools.py
sensei/migrations/__init__.py
sensei/migrations/env.py
sensei/migrations/script.py.mako
sensei/migrations/versions/40de6c7e554f_initial_schema.py
sensei/migrations/versions/8dfe094b42a0_query_messages_to_jsonb.py
sensei/migrations/versions/98d24c27bbe3_change_documents_url_constraint_to_url_.py
sensei/migrations/versions/__init__.py
sensei/scout/__init__.py
sensei/scout/__main__.py
sensei/scout/manager.py
sensei/scout/models.py
sensei/scout/operations.py
sensei/scout/repomap.py
sensei/scout/server.py
sensei/tome/__init__.py
sensei/tome/__main__.py
sensei/tome/chunker.py
sensei/tome/crawler.py
sensei/tome/parser.py
sensei/tome/server.py
sensei/tome/service.py
sensei/tools/__init__.py
sensei/tools/common.py
sensei/tools/context7.py
sensei/tools/exec_plan.py
sensei/tools/kura.py
sensei/tools/scout.py
sensei/tools/tavily.py
sensei/tools/tome.py
sensei_ai-1.4.0.dist-info/METADATA
sensei_ai-1.4.0.dist-info/WHEEL
sensei_ai-1.4.0.dist-info/entry_points.txt
sensei_ai-1.4.0.dist-info/top_level.txt
sensei_ai-1.4.0.dist-info/RECORD
