Metadata-Version: 2.4
Name: sensei-ai
Version: 1.4.0
Summary: Intelligent documentation agent for AI coding assistants
Author: alizain
License-Expression: MIT
Project-URL: Homepage, https://github.com/alizain/sensei
Project-URL: Repository, https://github.com/alizain/sensei
Classifier: Development Status :: 3 - Alpha
Classifier: Intended Audience :: Developers
Classifier: Programming Language :: Python :: 3
Classifier: Programming Language :: Python :: 3.13
Requires-Python: >=3.13
Requires-Dist: alembic>=1.14.0
Requires-Dist: anthropic>=0.75.0
Requires-Dist: asyncpg>=0.30.0
Requires-Dist: crawlee[httpx]>=0.6.0
Requires-Dist: fastapi-cli[standard]>=0.0.16
Requires-Dist: fastapi[standard]>=0.122.0
Requires-Dist: fastmcp>=2.13.3
Requires-Dist: greenlet>=3.2.4
Requires-Dist: httpx>=0.28.1
Requires-Dist: langfuse>=3.10.5
Requires-Dist: logfire>=4.15.1
Requires-Dist: mcp>=1.22.0
Requires-Dist: pydantic-ai>=1.22.0
Requires-Dist: pydantic-evals[logfire]
Requires-Dist: pydantic-settings>=2.11.7
Requires-Dist: pydantic>=2.11.7
Requires-Dist: ruff>=0.14.6
Requires-Dist: sqlalchemy[asyncio]>=2.0.44
Requires-Dist: tldextract>=5.1.0
Requires-Dist: uvicorn[standard]>=0.38.0
Provides-Extra: dev
Requires-Dist: pytest>=7.4.0; extra == "dev"
Requires-Dist: pytest-asyncio>=0.21.0; extra == "dev"
